mascope_tools/alignment/caching.py
mascope_tools/alignment/calibration.py
mascope_tools/alignment/utils.py
mascope_tools/alignment/__init__.py
mascope_tools/composition/constants.py
mascope_tools/composition/finder.py
mascope_tools/composition/heuristic_filter.py
mascope_tools/composition/models.py
mascope_tools/composition/utils.py
mascope_tools/composition/__init__.py
mascope_tools/__init__.py
mascope_tools-2025.10.16.dist-info/WHEEL
mascope_tools-2025.10.16.dist-info/METADATA
mascope_tools-2025.10.16.dist-info/RECORD
