Metadata-Version: 2.3
Name: mascope-tools
Version: 2025.10.16
Summary: Mascope's public library, containing tools for spectra postprocessing.
Author: Oskari Kausiala, Konstantin Tumashevich
Author-email: Oskari Kausiala <oskari.kausiala@karsa.fi>>, Konstantin Tumashevich <konstantin.tumashevich@karsa.fi>>
License: MIT
Classifier: Topic :: Scientific/Engineering :: Atmospheric Science
Classifier: Topic :: Software Development :: Libraries :: Python Modules
Requires-Dist: isospecpy>=2.2.3
Requires-Dist: mascope-sdk>=2025.10.14
Requires-Dist: numpy>=1.26
Requires-Dist: scipy>=1.16.1
Requires-Dist: pandas>=2.3.1
Requires-Dist: polars>=1.31.0
Requires-Dist: pyarrow>=21.0.0
Requires-Dist: pyteomics>=4.7.5
Requires-Dist: tqdm>=4.67.1
Maintainer: Oskari Kausiala, Konstantin Tumashevich
Maintainer-email: Oskari Kausiala <oskari.kausiala@karsa.fi>>, Konstantin Tumashevich <konstantin.tumashevich@karsa.fi>>
Requires-Python: >=3.12
Project-URL: Bug Tracker, https://github.com/Karsa-Oy/Mascope/issues
Project-URL: documentation, https://github.com/Karsa-Oy/Mascope
Project-URL: homepage, https://karsa.fi/
Project-URL: repository, https://github.com/Karsa-Oy/Mascope
